{"slots": [{"id": "slot-1773409842235-qnti", "selectedTrackIndex": null, "source": null, "tracks": []}, {"id": "autoset-slot-0", "selectedTrackIndex": 0, "source": {"id": "south-african-tribal-matrix__tribal-warehouse-ceremony", "name": "Ancestral Frequencies: Afro-House's Sacred Warehouse Rituals", "tree_type": "collection", "type": "tree_node"}, "tracks": [{"artist": "Swordman Kitala,Village Cuts", "bpm": 63, "bpm_level": 60, "has_audio": true, "id": 3983, "key": "9M", "title": "Digida", "year": 2022}, null, {"artist": "Ohxala", "bpm": 95, "bpm_level": 80, "has_audio": true, "id": 48, "key": "11M", "title": "Oba", "year": 2019}, {"artist": "ASA MOTO", "bpm": 108, "bpm_level": 90, "has_audio": true, "id": 3397, "key": "2D", "title": "Cacao", "year": 2021}, {"artist": "Osunlade,Carlos Mena", "bpm": 120, "bpm_level": 100, "has_audio": true, "id": 724, "key": "1M", "title": "Los Tambores Te Llaman - Casamena Remix", "year": 2016}, {"artist": "Osunlade,Carlos Mena", "bpm": 120, "bpm_level": 110, "has_audio": true, "id": 386, "key": "1M", "title": "Los Tambores Te Llaman - Casamena Remix", "year": 2016}, {"artist": "Tony Quattro,Nani Castle", "bpm": 127, "bpm_level": 120, "has_audio": true, "id": 1795, "key": "7M", "title": "Fuerza (feat. Nani Castle)", "year": 2017}, {"artist": "Povo", "bpm": 120, "bpm_level": 130, "has_audio": true, "id": 3431, "key": "7M", "title": "Uam Uam", "year": 2008}, {"artist": "Maria Gad\u00fa,Shapeless", "bpm": 125, "bpm_level": 140, "has_audio": true, "id": 1476, "key": "9M", "title": "Ax\u00e9 Acapella (Shapeless Versus Maria Gad\u00fa)", "year": 2016}, {"artist": "Mel\u00e9", "bpm": 130, "bpm_level": 150, "has_audio": true, "id": 2322, "key": "7M", "title": "Esperanza", "year": 2020}]}, {"id": "autoset-slot-1", "selectedTrackIndex": 4, "source": {"id": "70s-source-code__pan-african-spiritual-groove", "name": "Polyrhythmic Diaspora: Afrobeat's Global Conversation", "tree_type": "collection", "type": "tree_node"}, "tracks": [{"artist": "Francis Bebey", "bpm": 75.9, "bpm_level": 60, "has_audio": true, "id": 3173, "key": "3D", "title": "Fleur tropicale", "year": 2012}, {"artist": "Brian Eno", "bpm": 76.5, "bpm_level": 70, "has_audio": true, "id": 1027, "key": "4M", "title": "Juju Space Jazz", "year": 1983}, {"artist": "Susso", "bpm": 96.5, "bpm_level": 80, "has_audio": true, "id": 172, "key": "1M", "title": "Bani", "year": 2018}, {"artist": "Marijata", "bpm": 105.4, "bpm_level": 90, "has_audio": true, "id": 3197, "key": "12M", "title": "No Condition Is Permanent", "year": 1976}, {"artist": "Abayomy Afrobeat Orquestra", "bpm": 96, "bpm_level": 100, "has_audio": true, "id": 2823, "key": "7M", "title": "Malunguinho", "year": 2013}, {"artist": "Marijata", "bpm": 105.4, "bpm_level": 110, "has_audio": true, "id": 5248, "key": "12M", "title": "No Condition Is Permanent", "year": 1976}, {"artist": "Magic Drum Orchestra", "bpm": 115, "bpm_level": 120, "has_audio": true, "id": 277, "key": "8M", "title": "Get Up", "year": 2018}, {"artist": "The Bahama Soul Club, Kojato", "bpm": 110, "bpm_level": 130, "has_audio": true, "id": 2314, "key": "8M", "title": "Afro Shigida", "year": 2010}, {"artist": "Hot Chip, William Onyeabor", "bpm": 125.6, "bpm_level": 140, "has_audio": true, "id": 2338, "key": "6M", "title": "Atomic Bomb - Cover", "year": 2014}, {"artist": "Drummers Of The Societe Absolument Guinin", "bpm": 144.4, "bpm_level": 150, "has_audio": true, "id": 5782, "key": "11M", "title": "Bolero", "year": 2017}]}, {"id": "autoset-slot-2", "selectedTrackIndex": 3, "source": {"id": "south-african-tribal-matrix__tribal-warehouse-ceremony", "name": "Ancestral Frequencies: Afro-House's Sacred Warehouse Rituals", "tree_type": "collection", "type": "tree_node"}, "tracks": [null, null, {"artist": "The Unknown Cases", "bpm": 92, "bpm_level": 80, "has_audio": true, "id": 46, "key": "5M", "title": "Masimbabele", "year": 2019}, {"artist": "The Unknown Cases", "bpm": 92, "bpm_level": 90, "has_audio": true, "id": 224, "key": "5M", "title": "Masimbabele", "year": 2019}, {"artist": "Ranga", "bpm": 119.5, "bpm_level": 100, "has_audio": true, "id": 1102, "key": "3M", "title": "Banga 2", "year": 2019}, {"artist": "Mim Suleiman", "bpm": 130, "bpm_level": 110, "has_audio": true, "id": 1495, "key": "4M", "title": "Haki", "year": 2012}, {"artist": "Danvers", "bpm": 124.8, "bpm_level": 120, "has_audio": true, "id": 1829, "key": "10D", "title": "Aye Ata", "year": 2018}, {"artist": "D\u2019Monk", "bpm": 121.5, "bpm_level": 130, "has_audio": true, "id": 5057, "key": "7M", "title": "UZE", "year": 2019}, {"artist": "Tamburi Neri", "bpm": 121, "bpm_level": 140, "has_audio": true, "id": 1213, "key": "8D", "title": "Indio", "year": 2018}, null]}, {"id": "autoset-slot-3", "selectedTrackIndex": 3, "source": {"id": "south-african-tribal-matrix__tribal-warehouse-ceremony", "name": "Ancestral Frequencies: Afro-House's Sacred Warehouse Rituals", "tree_type": "collection", "type": "tree_node"}, "tracks": [null, null, null, {"artist": "The Unknown Cases", "bpm": 92, "bpm_level": 90, "has_audio": true, "id": 46, "key": "5M", "title": "Masimbabele", "year": 2019}, {"artist": "Thomash", "bpm": 105, "bpm_level": 100, "has_audio": true, "id": 4201, "key": "5M", "title": "Candomble - Original Mix", "year": 2014}, {"artist": "Mulya", "bpm": 116, "bpm_level": 110, "has_audio": true, "id": 3350, "key": "5M", "title": "Amos", "year": 2021}, {"artist": "Thomas Marlow,Kiko Navarro", "bpm": 120, "bpm_level": 120, "has_audio": true, "id": 1815, "key": "3M", "title": "Que Es - Kiko Navarro 4 la Troppa Re-Edit", "year": 2014}, {"artist": "Osunlade", "bpm": 120, "bpm_level": 130, "has_audio": true, "id": 3961, "key": "3M", "title": "Auto Machine", "year": 2020}, {"artist": "Austin Ato", "bpm": 123, "bpm_level": 140, "has_audio": true, "id": 1193, "key": "3D", "title": "Heat - Extended Mix", "year": 2022}, null]}, {"id": "autoset-slot-4", "selectedTrackIndex": 3, "source": {"id": "70s-source-code__pan-african-spiritual-groove", "name": "Polyrhythmic Diaspora: Afrobeat's Global Conversation", "tree_type": "collection", "type": "tree_node"}, "tracks": [{"artist": "Miriam Makeba", "bpm": 77.4, "bpm_level": 60, "has_audio": true, "id": 3295, "key": "1M", "title": "Xica da Silva", "year": 2014}, {"artist": "Jimi Tenor, Tony Allen", "bpm": 79.3, "bpm_level": 70, "has_audio": true, "id": 2878, "key": "3M", "title": "Selfish Gene", "year": 2009}, {"artist": "Susso", "bpm": 96.5, "bpm_level": 80, "has_audio": true, "id": 477, "key": "1M", "title": "Bani", "year": 2018}, {"artist": "Tony Allen, Theo Parrish, ESKA, Andrew Ashong", "bpm": 91.5, "bpm_level": 90, "has_audio": true, "id": 2865, "key": "2M", "title": "Day Like This Rework", "year": 2013}, {"artist": "Francis The Great", "bpm": 107.6, "bpm_level": 100, "has_audio": true, "id": 3192, "key": "1M", "title": "Look up in the Sky - N\u00e9gro Nature", "year": 2015}, {"artist": "Whitefield Brothers", "bpm": 110.3, "bpm_level": 110, "has_audio": true, "id": 6237, "key": "1M", "title": "Safari Strut", "year": 2010}, {"artist": "The Budos Band", "bpm": 122, "bpm_level": 120, "has_audio": true, "id": 6263, "key": "3M", "title": "Golden Dunes", "year": 2010}, {"artist": "Trio Ternura", "bpm": 112.3, "bpm_level": 130, "has_audio": true, "id": 3261, "key": "1M", "title": "Filhos De Zambi", "year": 1974}, {"artist": "War", "bpm": 120.5, "bpm_level": 140, "has_audio": true, "id": 1326, "key": "9M", "title": "Spill the Wine", "year": 1970}, null]}, {"id": "autoset-slot-5", "selectedTrackIndex": 4, "source": {"id": "70s-source-code__pan-african-spiritual-groove", "name": "Polyrhythmic Diaspora: Afrobeat's Global Conversation", "tree_type": "collection", "type": "tree_node"}, "tracks": [{"artist": "SPAZA,Nonku Phiri,Malcolm Jiyane,Gontse Makhene,Ariel Zamonsky", "bpm": 58.4, "bpm_level": 60, "has_audio": true, "id": 5043, "key": "7M", "title": "Sizwile", "year": 2020}, {"artist": "Pastor T.L. Barrett and the Youth for Christ Choir", "bpm": 85, "bpm_level": 70, "has_audio": true, "id": 4235, "key": "7M", "title": "Like a Ship", "year": 1971}, {"artist": "Mop Mop,Anthony Joseph", "bpm": 82, "bpm_level": 80, "has_audio": true, "id": 665, "key": "9M", "title": "The Barber", "year": 2008}, {"artist": "Ebo Taylor, Uhuru-Yenzu", "bpm": 107.5, "bpm_level": 90, "has_audio": true, "id": 2376, "key": "1M", "title": "Love And Death", "year": 1977}, {"artist": "Letta Mbulu", "bpm": 98.3, "bpm_level": 100, "has_audio": true, "id": 1389, "key": "12M", "title": "Nomalizo", "year": 1976}, {"artist": "Keleketla!, Coldcut, Tony Allen, Nono Nkoane, Thabang Tabane, Gally Ngoveni, Sibusile Xaba, Afla Sackey, Antibalas", "bpm": 120, "bpm_level": 110, "has_audio": true, "id": 3481, "key": "12M", "title": "Shepherd Song", "year": 2020}, {"artist": "Cos-Ber-Zam", "bpm": 121.2, "bpm_level": 120, "has_audio": true, "id": 2377, "key": "10M", "title": "Ne Noya", "year": 2010}, {"artist": "William Onyeabor", "bpm": 116.4, "bpm_level": 130, "has_audio": true, "id": 2368, "key": "6M", "title": "Atomic Bomb", "year": 2013}, {"artist": "Michael Jackson", "bpm": 122.2, "bpm_level": 140, "has_audio": true, "id": 2709, "key": "3D", "title": "Wanna Be Startin' Somethin'", "year": 1982}, null]}, {"id": "autoset-slot-6", "selectedTrackIndex": 3, "source": {"id": "south-african-tribal-matrix__organic-sun-ritual", "name": "Afro-House Mysticism: Global Sunset Ritual", "tree_type": "collection", "type": "tree_node"}, "tracks": [{"artist": "DEMI", "bpm": 63, "bpm_level": 60, "has_audio": false, "id": 3621, "key": "4M", "title": "B3 CabasaSolo", "year": 2018}, {"artist": "Vissungo", "bpm": 90, "bpm_level": 70, "has_audio": true, "id": 4165, "key": "1M", "title": "Xanana", "year": 2019}, {"artist": "Ohxala", "bpm": 95, "bpm_level": 80, "has_audio": true, "id": 226, "key": "11M", "title": "Oba", "year": 2019}, {"artist": "Ohxala", "bpm": 95, "bpm_level": 90, "has_audio": true, "id": 1284, "key": "11M", "title": "Oba", "year": 2019}, {"artist": "Magic Drum Orchestra", "bpm": 115, "bpm_level": 100, "has_audio": true, "id": 1181, "key": "8M", "title": "Get Up", "year": 2019}, {"artist": "Mulya", "bpm": 115, "bpm_level": 110, "has_audio": true, "id": 6225, "key": "5M", "title": "Amos", "year": 2021}, {"artist": "Kiko Navarro,Buika,Tedd Patterson", "bpm": 127, "bpm_level": 120, "has_audio": true, "id": 5301, "key": "12M", "title": "Mama Calling - Tedd Patterson Remix", "year": 2014}, {"artist": "Tamburi Neri", "bpm": 121, "bpm_level": 130, "has_audio": true, "id": 989, "key": "8D", "title": "Indio", "year": 2019}, {"artist": "De Gama", "bpm": 126, "bpm_level": 140, "has_audio": true, "id": 1971, "key": "12M", "title": "Afrika", "year": 2011}, null]}, {"id": "autoset-slot-7", "selectedTrackIndex": 4, "source": {"id": "70s-source-code__pan-african-spiritual-groove", "name": "Polyrhythmic Diaspora: Afrobeat's Global Conversation", "tree_type": "collection", "type": "tree_node"}, "tracks": [{"artist": "Francis Bebey", "bpm": 55.3, "bpm_level": 60, "has_audio": true, "id": 1339, "key": "11M", "title": "The Coffee Cola Song", "year": 1981}, {"artist": "Leal Brito,Odete,Sandoval Dias,Ze Menezes", "bpm": 85.6, "bpm_level": 70, "has_audio": true, "id": 323, "key": "12D", "title": "Mulato Bamba", "year": 1978}, {"artist": "Ibibio Sound Machine", "bpm": 98.3, "bpm_level": 80, "has_audio": true, "id": 3456, "key": "11M", "title": "Electricity", "year": 2022}, {"artist": "Susso", "bpm": 96.5, "bpm_level": 90, "has_audio": true, "id": 1103, "key": "1M", "title": "Bani", "year": 2019}, {"artist": "Ibibio Sound Machine", "bpm": 98.3, "bpm_level": 100, "has_audio": true, "id": 3401, "key": "11M", "title": "Electricity", "year": 2022}, {"artist": "Manu Dibango", "bpm": 115, "bpm_level": 110, "has_audio": true, "id": 5045, "key": "12M", "title": "Soul Makossa", "year": 2000}, {"artist": "Banda Black Rio", "bpm": 101.2, "bpm_level": 120, "has_audio": true, "id": 2839, "key": "1M", "title": "Vidigal", "year": 2002}, {"artist": "Oby Onyioha", "bpm": 116.2, "bpm_level": 130, "has_audio": true, "id": 3995, "key": "9M", "title": "Enjoy Your Life", "year": 2015}, {"artist": "Bebeto", "bpm": 128.9, "bpm_level": 140, "has_audio": true, "id": 3282, "key": "2M", "title": "Princesa Negra De Angola", "year": 1976}, null]}, {"id": "autoset-slot-8", "selectedTrackIndex": 5, "source": {"id": "70s-source-code__pan-african-spiritual-groove", "name": "Polyrhythmic Diaspora: Afrobeat's Global Conversation", "tree_type": "collection", "type": "tree_node"}, "tracks": [{"artist": "The Budos Band", "bpm": 57.4, "bpm_level": 60, "has_audio": true, "id": 624, "key": "2M", "title": "The Volcano Song", "year": 2009}, {"artist": "Toni Tornado", "bpm": 86, "bpm_level": 70, "has_audio": true, "id": 3224, "key": "5D", "title": "Me Libertei", "year": 1971}, {"artist": "Zazou Bikaye", "bpm": 92, "bpm_level": 80, "has_audio": true, "id": 1251, "key": "3M", "title": "M'PasiI Ya M'Pamba", "year": 1983}, {"artist": "Nickodemus,Polo", "bpm": 95, "bpm_level": 90, "has_audio": true, "id": 241, "key": "11M", "title": "The Global Village - Vocal Version", "year": 2008}, {"artist": "SAULT", "bpm": 89.8, "bpm_level": 100, "has_audio": true, "id": 5088, "key": "12D", "title": "Warrior", "year": 2022}, {"artist": "Marijata", "bpm": 105.4, "bpm_level": 110, "has_audio": true, "id": 3197, "key": "12M", "title": "No Condition Is Permanent", "year": 1976}, {"artist": "Amadou & Mariam", "bpm": 118, "bpm_level": 120, "has_audio": true, "id": 1626, "key": "1M", "title": "Bofou Safou", "year": 2008}, {"artist": "Ekambi Brillant,John Talabot,Pional", "bpm": 118, "bpm_level": 130, "has_audio": true, "id": 1093, "key": "2M", "title": "Afrika Afrika - John Talabot & Pional 'Lost Scripts' Rerub", "year": 2012}, null, null]}, {"id": "autoset-slot-9", "selectedTrackIndex": 6, "source": {"id": "70s-source-code__afrobeat-jazz-funk-renaissance", "name": "Afrobeat Continuum: From Fela's Lagos to Global Dancefloors", "tree_type": "collection", "type": "tree_node"}, "tracks": [null, {"artist": "Mop Mop,Anthony Joseph", "bpm": 82, "bpm_level": 70, "has_audio": true, "id": 1338, "key": "9M", "title": "The Barber", "year": 2014}, {"artist": "Gordon Koang, Sleep D", "bpm": 100, "bpm_level": 80, "has_audio": true, "id": 3488, "key": "11M", "title": "Y Dah - Sleep D Remix (Radio Edit)", "year": 2021}, {"artist": "Aron Ottignon,\u00ccF\u00c9,Lucas Croon", "bpm": 108.3, "bpm_level": 90, "has_audio": true, "id": 4082, "key": "2M", "title": "Ore Y\u00e8y\u00e9 O - Lucas Croon Remix", "year": 2020}, {"artist": "Magic Drum Orchestra", "bpm": 115, "bpm_level": 100, "has_audio": true, "id": 898, "key": "8M", "title": "Get Up", "year": 2016}, {"artist": "Letta Mbulu", "bpm": 98.3, "bpm_level": 110, "has_audio": true, "id": 6235, "key": "12M", "title": "Nomalizo", "year": 1996}, {"artist": "Tony Allen,Hugh Masekela", "bpm": 117, "bpm_level": 120, "has_audio": true, "id": 5048, "key": "10D", "title": "We've Landed", "year": 2020}, {"artist": "The Budos Band", "bpm": 122.7, "bpm_level": 130, "has_audio": true, "id": 5297, "key": "3M", "title": "Golden Dunes", "year": 2010}, {"artist": "The Budos Band", "bpm": 122.7, "bpm_level": 140, "has_audio": true, "id": 4009, "key": "3M", "title": "Golden Dunes", "year": 2010}, null]}, {"id": "autoset-slot-10", "selectedTrackIndex": 0, "source": {"id": "70s-source-code__afrobeat-jazz-funk-renaissance", "name": "Afrobeat Continuum: From Fela's Lagos to Global Dancefloors", "tree_type": "collection", "type": "tree_node"}, "tracks": [{"artist": "Manu Dibango", "bpm": 0, "bpm_level": 60, "has_audio": true, "id": 5342, "key": "", "title": "Coconut", "year": 1972}, null, {"artist": "Nohelani Cypriano, Peter Moon, Jerry Byrd, Kapono Beamer, Roscoe Wright, Master Henry Gibson, John Raposa, Kata Maduli, Wayne Hobbs, Henry Kapono, Winner Female Vocalist of the Year Hoku, Winner Contemporary Hawaiian Album of the Year Hoku", "bpm": 95.5, "bpm_level": 80, "has_audio": true, "id": 5695, "key": "12M", "title": "Lihue", "year": 1978}, {"artist": "Nu Genea, Tony Allen", "bpm": 105, "bpm_level": 90, "has_audio": true, "id": 6196, "key": "10M", "title": "The Birds Rejoice", "year": 2016}, {"artist": "Cosmos Universal Band", "bpm": 111.3, "bpm_level": 100, "has_audio": true, "id": 5503, "key": "2M", "title": "Third Eye", "year": 2016}, {"artist": "Africaine 808,Wolf M\u00fcller", "bpm": 109, "bpm_level": 110, "has_audio": true, "id": 1309, "key": "5D", "title": "Rhythm Is All You Can Dance - Wolf Muller Remix", "year": 2014}, {"artist": "William Onyeabor", "bpm": 116.4, "bpm_level": 120, "has_audio": true, "id": 5193, "key": "6M", "title": "Atomic Bomb", "year": 2013}, null, null, null]}, {"id": "autoset-slot-11", "selectedTrackIndex": 0, "source": {"id": "70s-source-code__pan-african-spiritual-groove", "name": "Polyrhythmic Diaspora: Afrobeat's Global Conversation", "tree_type": "collection", "type": "tree_node"}, "tracks": [{"artist": "Francis Bebey", "bpm": 55.3, "bpm_level": 60, "has_audio": true, "id": 1339, "key": "11M", "title": "The Coffee Cola Song", "year": 1981}, null, {"artist": "Susso", "bpm": 96.5, "bpm_level": 80, "has_audio": true, "id": 39, "key": "1M", "title": "Bani", "year": 2019}, {"artist": "Oneness Of Juju", "bpm": 97.9, "bpm_level": 90, "has_audio": true, "id": 2993, "key": "8D", "title": "African Rhythms", "year": 2017}, {"artist": "Patchworks Ginger Xpress", "bpm": 116, "bpm_level": 100, "has_audio": true, "id": 3968, "key": "9M", "title": "Brothers On The Slide", "year": 1974}, {"artist": "Amadou & Mariam", "bpm": 106.3, "bpm_level": 110, "has_audio": true, "id": 3502, "key": "2M", "title": "Je pense \u00e0 toi", "year": 1998}, {"artist": "Lafayette Afro Rock Band", "bpm": 104.6, "bpm_level": 120, "has_audio": true, "id": 5070, "key": "6M", "title": "Darkest Light - Remastered", "year": 2021}, null, null, null]}, {"id": "autoset-slot-12", "selectedTrackIndex": 4, "source": {"id": "south-african-tribal-matrix__tribal-warehouse-ceremony", "name": "Ancestral Frequencies: Afro-House's Sacred Warehouse Rituals", "tree_type": "collection", "type": "tree_node"}, "tracks": [null, null, null, {"artist": "ASA MOTO", "bpm": 108, "bpm_level": 90, "has_audio": true, "id": 3447, "key": "2D", "title": "Cacao", "year": 2021}, {"artist": "Joutro Mundo", "bpm": 100, "bpm_level": 100, "has_audio": true, "id": 2828, "key": "9M", "title": "Olhos De S\u00e1", "year": 2017}, {"artist": "Osunlade,Carlos Mena", "bpm": 120, "bpm_level": 110, "has_audio": true, "id": 992, "key": "10M", "title": "Los Tambores Te Llaman - Casamena Remix", "year": 2015}, {"artist": "Kino Todo,Tesfit Asgodom,Red Axes", "bpm": 120, "bpm_level": 120, "has_audio": true, "id": 432, "key": "10M", "title": "Gidafi Na feat. Asgodom - Red Axes Edit", "year": 2017}, {"artist": "Thomash", "bpm": 110, "bpm_level": 130, "has_audio": true, "id": 41, "key": "7M", "title": "Candomble - Dreems Remix", "year": 2016}, {"artist": "DEMI", "bpm": 126, "bpm_level": 140, "has_audio": false, "id": 3608, "key": "2M", "title": "A1-IntroConga", "year": 2018}, null]}, {"id": "autoset-slot-13", "selectedTrackIndex": 5, "source": {"id": "70s-source-code__afro-warehouse-futurism", "name": "Lagos-Detroit Axis: Afrobeat Meets Warehouse Minimalism", "tree_type": "collection", "type": "tree_node"}, "tracks": [{"artist": "Falle Nioke,Ghost Culture", "bpm": 57, "bpm_level": 60, "has_audio": true, "id": 4205, "key": "12M", "title": "Leywole - Edit", "year": 2021}, null, {"artist": "Burna Boy", "bpm": 96, "bpm_level": 80, "has_audio": true, "id": 2756, "key": "12M", "title": "Odogwu", "year": 2020}, {"artist": "Nu Genea, Tony Allen", "bpm": 105, "bpm_level": 90, "has_audio": true, "id": 6140, "key": "7M", "title": "Prelude", "year": 2016}, {"artist": "Peter Power", "bpm": 105, "bpm_level": 100, "has_audio": true, "id": 47, "key": "12M", "title": "Mori Baka", "year": 2018}, {"artist": "Tony Allen", "bpm": 114.6, "bpm_level": 110, "has_audio": true, "id": 3052, "key": "9M", "title": "Road Close - Dance Dub", "year": 1985}, {"artist": "SAULT", "bpm": 120.4, "bpm_level": 120, "has_audio": true, "id": 1239, "key": "1M", "title": "Let Me Go", "year": 2019}, {"artist": "Zotobr\u00e9", "bpm": 116.6, "bpm_level": 130, "has_audio": true, "id": 1799, "key": "12M", "title": "Lagen", "year": 2016}, null, null]}, {"id": "autoset-slot-14", "selectedTrackIndex": 4, "source": {"id": "70s-source-code__pan-african-spiritual-groove", "name": "Polyrhythmic Diaspora: Afrobeat's Global Conversation", "tree_type": "collection", "type": "tree_node"}, "tracks": [null, null, {"artist": "Barbatuques", "bpm": 95.7, "bpm_level": 80, "has_audio": true, "id": 1099, "key": "6M", "title": "Bai\u00e3o Destemperado", "year": 2013}, {"artist": "Mandrill", "bpm": 105.4, "bpm_level": 90, "has_audio": true, "id": 2040, "key": "1M", "title": "Fencewalk", "year": 2001}, {"artist": "Lafayette Afro Rock Band", "bpm": 104.6, "bpm_level": 100, "has_audio": true, "id": 5070, "key": "6M", "title": "Darkest Light - Remastered", "year": 2021}, {"artist": "Francis Bebey", "bpm": 103.4, "bpm_level": 110, "has_audio": true, "id": 4223, "key": "4M", "title": "Forest Nativity", "year": 2014}, null, null, null, null]}, {"id": "autoset-slot-15", "selectedTrackIndex": 4, "source": {"id": "kingston-diaspora-pressure__global-riddim-mutations", "name": "Crescent City Roots: Caribbean Rhythms in American Soul", "tree_type": "collection", "type": "tree_node"}, "tracks": [{"artist": "King Curtis", "bpm": 56.5, "bpm_level": 60, "has_audio": false, "id": 4481, "key": "2M", "title": "Memphis Soul Stew", "year": 1967}, {"artist": "Quantic,Flowering Inferno", "bpm": 70.7, "bpm_level": 70, "has_audio": true, "id": 316, "key": "10M", "title": "Echate Palla", "year": 2008}, {"artist": "Rare Essence, Raheem DeVaughn, Dee Boy", "bpm": 94, "bpm_level": 80, "has_audio": true, "id": 2296, "key": "1M", "title": "Tryna Go", "year": 2016}, {"artist": "Prince Fatty, Horseman", "bpm": 102.2, "bpm_level": 90, "has_audio": true, "id": 3534, "key": "3D", "title": "Insane in the Brain", "year": 2010}, {"artist": "Bacao Rhythm & Steel Band", "bpm": 103.9, "bpm_level": 100, "has_audio": true, "id": 280, "key": "1M", "title": "Laventille Road March", "year": 2016}, {"artist": "King Floyd", "bpm": 104.3, "bpm_level": 110, "has_audio": true, "id": 3533, "key": "3M", "title": "Groove Me", "year": 1994}, {"artist": "Lee Dorsey", "bpm": 138.1, "bpm_level": 120, "has_audio": true, "id": 2439, "key": "8M", "title": "Who's Gonna Help a Brother Get Further?", "year": 2006}, {"artist": "Tabu Ley Rochereau", "bpm": 123.4, "bpm_level": 130, "has_audio": true, "id": 1385, "key": "4D", "title": "Hafi Deo", "year": 1985}, {"artist": "Rufus Thomas", "bpm": 122.6, "bpm_level": 140, "has_audio": true, "id": 1262, "key": "11M", "title": "Mashed Potatoes", "year": 1962}, {"artist": "Lord Shorty & Vibrations International", "bpm": 136.7, "bpm_level": 150, "has_audio": true, "id": 4630, "key": "7M", "title": "Vibrations Groove", "year": 2012}]}, {"id": "autoset-slot-16", "selectedTrackIndex": 5, "source": {"id": "70s-source-code__pan-african-spiritual-groove", "name": "Polyrhythmic Diaspora: Afrobeat's Global Conversation", "tree_type": "collection", "type": "tree_node"}, "tracks": [null, null, null, null, null, {"artist": "Ebo Taylor, Uhuru-Yenzu", "bpm": 107.5, "bpm_level": 110, "has_audio": true, "id": 2376, "key": "1M", "title": "Love And Death", "year": 1977}, null, null, null, null]}, {"id": "autoset-slot-17", "selectedTrackIndex": 5, "source": {"id": "south-african-tribal-matrix__tribal-warehouse-ceremony", "name": "Ancestral Frequencies: Afro-House's Sacred Warehouse Rituals", "tree_type": "collection", "type": "tree_node"}, "tracks": [null, null, null, {"artist": "ASA MOTO", "bpm": 108, "bpm_level": 90, "has_audio": true, "id": 3969, "key": "2D", "title": "Cacao", "year": 2021}, {"artist": "Thomash", "bpm": 110, "bpm_level": 100, "has_audio": true, "id": 1124, "key": "7M", "title": "Candomble - Dreems Remix", "year": 2016}, {"artist": "ASA MOTO", "bpm": 108, "bpm_level": 110, "has_audio": true, "id": 3397, "key": "2D", "title": "Cacao", "year": 2021}, {"artist": "Kiko Navarro,Buika,Tedd Patterson", "bpm": 127, "bpm_level": 120, "has_audio": true, "id": 1255, "key": "12M", "title": "Mama Calling - Tedd Patterson Remix", "year": 2015}, {"artist": "Osunlade,Carlos Mena", "bpm": 120, "bpm_level": 130, "has_audio": true, "id": 5149, "key": "1M", "title": "Los Tambores Te Llaman - Casamena Remix", "year": 2020}, {"artist": "Africaine 808", "bpm": 120.2, "bpm_level": 140, "has_audio": true, "id": 1439, "key": "12M", "title": "Tummy, Tummy", "year": 2014}, null]}, {"id": "autoset-slot-18", "selectedTrackIndex": 5, "source": {"id": "70s-source-code__pan-african-spiritual-groove", "name": "Polyrhythmic Diaspora: Afrobeat's Global Conversation", "tree_type": "collection", "type": "tree_node"}, "tracks": [null, null, null, null, null, {"artist": "The Bahama Soul Club, Kojato", "bpm": 110, "bpm_level": 110, "has_audio": true, "id": 2314, "key": "8M", "title": "Afro Shigida", "year": 2010}, null, null, null, null]}, {"id": "autoset-slot-19", "selectedTrackIndex": 9, "source": {"id": "south-african-tribal-matrix__tribal-warehouse-ceremony", "name": "Ancestral Frequencies: Afro-House's Sacred Warehouse Rituals", "tree_type": "collection", "type": "tree_node"}, "tracks": [null, null, null, {"artist": "Maria Beraldo", "bpm": 100, "bpm_level": 90, "has_audio": true, "id": 3377, "key": "11M", "title": "Sussussussu", "year": 2018}, {"artist": "Sultan Shakes", "bpm": 120, "bpm_level": 100, "has_audio": true, "id": 6074, "key": "5D", "title": "Oud Ou Ray", "year": 2017}, {"artist": "Anilza Leoni", "bpm": 110.3, "bpm_level": 110, "has_audio": true, "id": 3246, "key": "1M", "title": "Balumba", "year": 2012}, {"artist": "Rio Rhythm Band", "bpm": 116.2, "bpm_level": 120, "has_audio": true, "id": 6261, "key": "11M", "title": "Cuban Jakkin'", "year": 2012}, {"artist": "Raw Instinct, DJ Gregory", "bpm": 124.2, "bpm_level": 130, "has_audio": true, "id": 2905, "key": "4D", "title": "Grande de folie - DJ Gregory's Prassay Dub", "year": 2000}, {"artist": "Africaine 808", "bpm": 120.2, "bpm_level": 140, "has_audio": true, "id": 1825, "key": "12M", "title": "Tummy, Tummy", "year": 2013}, {"artist": "Umoja", "bpm": 175.5, "bpm_level": 150, "has_audio": true, "id": 745, "key": "11M", "title": "Umboweti - Original Mix", "year": 2016}]}, {"id": "autoset-slot-20", "selectedTrackIndex": 6, "source": {"id": "afro-diasporic-bass-lagos-rio-johannesburg__afro-warehouse-futurism", "name": "Afrobeat's Electronic Continuum", "tree_type": "collection", "type": "tree_node"}, "tracks": [null, {"artist": "Ohxala", "bpm": 90, "bpm_level": 70, "has_audio": true, "id": 216, "key": "1M", "title": "Lekeleke", "year": 2023}, {"artist": "Susso", "bpm": 96.5, "bpm_level": 80, "has_audio": true, "id": 5226, "key": "1M", "title": "Bani", "year": 2016}, {"artist": "Tony Allen", "bpm": 106, "bpm_level": 90, "has_audio": true, "id": 5588, "key": "3D", "title": "Afrobeat Jam", "year": 2012}, {"artist": "kadiata", "bpm": 108, "bpm_level": 100, "has_audio": true, "id": 1706, "key": "6M", "title": "On Tap", "year": 2019}, {"artist": "Idris Elba, Kah-Lo", "bpm": 124, "bpm_level": 110, "has_audio": true, "id": 3307, "key": "11M", "title": "Ballie", "year": 2019}, {"artist": "Oby Onyioha", "bpm": 116.2, "bpm_level": 120, "has_audio": true, "id": 2372, "key": "10M", "title": "Enjoy Your Life", "year": 2015}, {"artist": "Romie Singh", "bpm": 120, "bpm_level": 130, "has_audio": true, "id": 3974, "key": "11M", "title": "Cry Freedom", "year": 2019}, {"artist": "Red Axes,Abr\u00e3o,Rebolledo,Adam Ten", "bpm": 122, "bpm_level": 140, "has_audio": true, "id": 4778, "key": "3D", "title": "Caminho De Dreyfus (Rebolledo Remix) (Adam Ten 303 Retouch)", "year": 2022}, null]}, {"id": "autoset-slot-21", "selectedTrackIndex": 6, "source": {"id": "70s-source-code__pan-african-spiritual-groove", "name": "Polyrhythmic Diaspora: Afrobeat's Global Conversation", "tree_type": "collection", "type": "tree_node"}, "tracks": [null, null, null, null, null, null, {"artist": "William Onyeabor", "bpm": 116.4, "bpm_level": 120, "has_audio": true, "id": 2368, "key": "6M", "title": "Atomic Bomb", "year": 2013}, null, null, null]}, {"id": "autoset-slot-22", "selectedTrackIndex": 6, "source": {"id": "south-african-tribal-matrix__tribal-warehouse-ceremony", "name": "Ancestral Frequencies: Afro-House's Sacred Warehouse Rituals", "tree_type": "collection", "type": "tree_node"}, "tracks": [null, null, null, {"artist": "Maria Beraldo", "bpm": 100, "bpm_level": 90, "has_audio": true, "id": 6198, "key": "11M", "title": "Sussussussu", "year": 2018}, {"artist": "Thomash", "bpm": 110, "bpm_level": 100, "has_audio": true, "id": 486, "key": "7M", "title": "Candomble - Dreems Remix", "year": 2016}, {"artist": "Osunlade,Carlos Mena", "bpm": 120, "bpm_level": 110, "has_audio": true, "id": 1802, "key": "1M", "title": "Los Tambores Te Llaman - Casamena Remix", "year": 2020}, {"artist": "Mulya", "bpm": 116, "bpm_level": 120, "has_audio": true, "id": 3350, "key": "5M", "title": "Amos", "year": 2021}, {"artist": "Kiko Navarro,Buika,Tedd Patterson", "bpm": 127, "bpm_level": 130, "has_audio": true, "id": 1884, "key": "12M", "title": "Mama Calling - Tedd Patterson Remix", "year": 2014}, {"artist": "Mr Joe", "bpm": 124, "bpm_level": 140, "has_audio": true, "id": 6139, "key": "12M", "title": "People Of Wakanda", "year": 2023}, null]}, {"id": "autoset-slot-23", "selectedTrackIndex": 6, "source": {"id": "modern-diaspora-revival__afrobeat-jazz-funk-renaissance", "name": "Afrobeat Refracted: Mediterranean Studio Craft & Balearic Edits", "tree_type": "collection", "type": "tree_node"}, "tracks": [{"artist": "Falle Nioke,sir Was", "bpm": 75, "bpm_level": 60, "has_audio": true, "id": 4248, "key": "4M", "title": "Wonama yo ema", "year": 2021}, {"artist": "Mop Mop,Anthony Joseph", "bpm": 82, "bpm_level": 70, "has_audio": true, "id": 812, "key": "9M", "title": "The Barber", "year": 2014}, {"artist": "Mop Mop,Anthony Joseph", "bpm": 82, "bpm_level": 80, "has_audio": true, "id": 613, "key": "9M", "title": "The Barber", "year": 2014}, {"artist": "Mop Mop,Anthony Joseph", "bpm": 82, "bpm_level": 90, "has_audio": true, "id": 240, "key": "9M", "title": "The Barber", "year": 2014}, null, null, {"artist": "Ekambi Brillant,John Talabot,Pional", "bpm": 118, "bpm_level": 120, "has_audio": true, "id": 695, "key": "2M", "title": "Afrika Afrika - John Talabot & Pional 'Lost Scripts' Rerub", "year": 2012}, null, null, null]}, {"id": "autoset-slot-24", "selectedTrackIndex": 0, "source": {"id": "70s-source-code__pan-african-spiritual-groove", "name": "Polyrhythmic Diaspora: Afrobeat's Global Conversation", "tree_type": "collection", "type": "tree_node"}, "tracks": [{"artist": "SPAZA,Nonku Phiri,Malcolm Jiyane,Gontse Makhene,Ariel Zamonsky", "bpm": 58.4, "bpm_level": 60, "has_audio": true, "id": 5043, "key": "7M", "title": "Sizwile", "year": 2020}, null, null, null, null, null, null, null, null, null]}, {"id": "autoset-slot-25", "selectedTrackIndex": 6, "source": {"id": "south-african-tribal-matrix__tribal-warehouse-ceremony", "name": "Ancestral Frequencies: Afro-House's Sacred Warehouse Rituals", "tree_type": "collection", "type": "tree_node"}, "tracks": [null, null, null, {"artist": "Charanga 76", "bpm": 105.8, "bpm_level": 90, "has_audio": true, "id": 5477, "key": "2M", "title": "Music Trance", "year": 2010}, {"artist": "Osunlade,Carlos Mena", "bpm": 120, "bpm_level": 100, "has_audio": true, "id": 1245, "key": "1M", "title": "Los Tambores Te Llaman - Casamena Remix", "year": 2016}, {"artist": "Alex Guesta", "bpm": 123, "bpm_level": 110, "has_audio": true, "id": 1967, "key": "7D", "title": "Kayamba - Tribal Mix", "year": 2017}, {"artist": "Osunlade,Carlos Mena", "bpm": 120, "bpm_level": 120, "has_audio": true, "id": 992, "key": "10M", "title": "Los Tambores Te Llaman - Casamena Remix", "year": 2015}, {"artist": "Thomash", "bpm": 110, "bpm_level": 130, "has_audio": true, "id": 5261, "key": "7M", "title": "Candomble - Dreems Remix", "year": 2014}, {"artist": "Kiko Navarro,Buika,Tedd Patterson", "bpm": 127, "bpm_level": 140, "has_audio": true, "id": 1937, "key": "12M", "title": "Mama Calling - Tedd Patterson Remix", "year": 2014}, null]}, {"id": "autoset-slot-26", "selectedTrackIndex": 5, "source": {"id": "70s-source-code__pan-african-spiritual-groove", "name": "Polyrhythmic Diaspora: Afrobeat's Global Conversation", "tree_type": "collection", "type": "tree_node"}, "tracks": [null, null, null, null, null, {"artist": "Manu Dibango", "bpm": 115, "bpm_level": 110, "has_audio": true, "id": 5045, "key": "12M", "title": "Soul Makossa", "year": 2000}, null, null, null, null]}, {"id": "autoset-slot-27", "selectedTrackIndex": 6, "source": {"id": "south-african-tribal-matrix__tribal-warehouse-ceremony", "name": "Ancestral Frequencies: Afro-House's Sacred Warehouse Rituals", "tree_type": "collection", "type": "tree_node"}, "tracks": [null, null, null, null, {"artist": "Elizabeth!", "bpm": 115.9, "bpm_level": 100, "has_audio": true, "id": 3236, "key": "10M", "title": "Vou Falar-Lhe Francamente", "year": 2014}, {"artist": "Jungle By Night, Ron Trent", "bpm": 124, "bpm_level": 110, "has_audio": true, "id": 2933, "key": "12M", "title": "Spending Week - Ron Trent Remix", "year": 2020}, {"artist": "Africaine 808", "bpm": 120.2, "bpm_level": 120, "has_audio": true, "id": 1825, "key": "12M", "title": "Tummy, Tummy", "year": 2013}, {"artist": "Alex Guesta", "bpm": 124, "bpm_level": 130, "has_audio": true, "id": 1972, "key": "8M", "title": "Babarabatiri - Alex Guesta Tribal Mix", "year": 2017}, {"artist": "Mel\u00e9", "bpm": 125, "bpm_level": 140, "has_audio": true, "id": 1343, "key": "2D", "title": "The Latin Track", "year": 2015}, null]}, {"id": "autoset-slot-28", "selectedTrackIndex": 6, "source": {"id": "south-african-tribal-matrix__tribal-warehouse-ceremony", "name": "Ancestral Frequencies: Afro-House's Sacred Warehouse Rituals", "tree_type": "collection", "type": "tree_node"}, "tracks": [null, null, null, null, null, {"artist": "DEMI", "bpm": 126, "bpm_level": 110, "has_audio": false, "id": 3625, "key": "1M", "title": "Snare-Carnevale", "year": 2015}, {"artist": "Osunlade,Carlos Mena", "bpm": 120, "bpm_level": 120, "has_audio": true, "id": 386, "key": "1M", "title": "Los Tambores Te Llaman - Casamena Remix", "year": 2016}, {"artist": "Kino Todo,Tesfit Asgodom,Red Axes", "bpm": 120, "bpm_level": 130, "has_audio": true, "id": 1183, "key": "10M", "title": "Gidafi Na feat. Asgodom - Red Axes Edit", "year": 2017}, {"artist": "She's Drunk,Sho Madjozi,Shy One", "bpm": 126, "bpm_level": 140, "has_audio": true, "id": 4334, "key": "3D", "title": "Amadoda - Shy One Remix", "year": 2019}, null]}, {"id": "autoset-slot-29", "selectedTrackIndex": 6, "source": {"id": "afro-diasporic-bass-lagos-rio-johannesburg__afro-warehouse-futurism", "name": "Afrobeat's Electronic Continuum", "tree_type": "collection", "type": "tree_node"}, "tracks": [null, {"artist": "Curumin, Cam\u00f5es, Lucas Alves", "bpm": 87, "bpm_level": 70, "has_audio": true, "id": 2811, "key": "12M", "title": "Bora Passear (del\u00edcia Remix)", "year": 2020}, {"artist": "Nitty Scott,Zap Mama", "bpm": 100, "bpm_level": 80, "has_audio": true, "id": 437, "key": "7M", "title": "La Diaspora (feat. Zap Mama)", "year": 2016}, {"artist": "Barbatuques", "bpm": 95.7, "bpm_level": 90, "has_audio": true, "id": 697, "key": "6M", "title": "Bai\u00e3o Destemperado", "year": 2013}, {"artist": "Romare", "bpm": 106.4, "bpm_level": 100, "has_audio": true, "id": 1470, "key": "12D", "title": "All Night", "year": 2015}, {"artist": "Tony Allen", "bpm": 117.8, "bpm_level": 110, "has_audio": true, "id": 2863, "key": "8M", "title": "Ariya", "year": 2011}, {"artist": "Idris Elba, Kah-Lo", "bpm": 124, "bpm_level": 120, "has_audio": true, "id": 3307, "key": "11M", "title": "Ballie", "year": 2019}, null, null, null]}, {"id": "autoset-slot-30", "selectedTrackIndex": 6, "source": {"id": "south-african-tribal-matrix__organic-sun-ritual", "name": "Afro-House Mysticism: Global Sunset Ritual", "tree_type": "collection", "type": "tree_node"}, "tracks": [null, null, {"artist": "Kike Harvey", "bpm": 98.5, "bpm_level": 80, "has_audio": true, "id": 5054, "key": "8M", "title": "Pachangon 2", "year": 1993}, {"artist": "Aleksandir,ASA MOTO", "bpm": 110, "bpm_level": 90, "has_audio": true, "id": 748, "key": "10M", "title": "Yamaha - Asa Moto Remix", "year": 2018}, {"artist": "Polo & Pan,ASA MOTO", "bpm": 120, "bpm_level": 100, "has_audio": true, "id": 711, "key": "10D", "title": "Gengis - Asa Moto Remix", "year": 2019}, {"artist": "ELO, Mystic Bill", "bpm": 124, "bpm_level": 110, "has_audio": true, "id": 6231, "key": "9D", "title": "La Pampara (Mystic Bill Remix)", "year": 2023}, {"artist": "Magic Drum Orchestra", "bpm": 115, "bpm_level": 120, "has_audio": true, "id": 1181, "key": "8M", "title": "Get Up", "year": 2019}, {"artist": "Klein Zage,Local Artist", "bpm": 125, "bpm_level": 130, "has_audio": true, "id": 4112, "key": "7M", "title": "She's Out There - Local Artist Cult Mix", "year": 2019}, {"artist": "Klein Zage", "bpm": 120, "bpm_level": 140, "has_audio": true, "id": 3388, "key": "5D", "title": "Womanhood", "year": 2019}, null]}, {"id": "autoset-slot-31", "selectedTrackIndex": 3, "source": {"id": "70s-source-code__pan-african-spiritual-groove", "name": "Polyrhythmic Diaspora: Afrobeat's Global Conversation", "tree_type": "collection", "type": "tree_node"}, "tracks": [null, null, null, {"artist": "SAULT", "bpm": 89.8, "bpm_level": 90, "has_audio": true, "id": 5088, "key": "12D", "title": "Warrior", "year": 2022}, null, null, null, null, null, null]}, {"id": "autoset-slot-32", "selectedTrackIndex": 6, "source": {"id": "south-african-tribal-matrix__tribal-warehouse-ceremony", "name": "Ancestral Frequencies: Afro-House's Sacred Warehouse Rituals", "tree_type": "collection", "type": "tree_node"}, "tracks": [null, null, null, null, null, {"artist": "Aili, Transistorcake", "bpm": 121, "bpm_level": 110, "has_audio": true, "id": 3407, "key": "3M", "title": "Pari Pari", "year": 2021}, {"artist": "Danvers", "bpm": 124.8, "bpm_level": 120, "has_audio": true, "id": 1829, "key": "10D", "title": "Aye Ata", "year": 2018}, null, null, null]}, {"id": "autoset-slot-33", "selectedTrackIndex": 7, "source": {"id": "south-african-tribal-matrix__tribal-warehouse-ceremony", "name": "Ancestral Frequencies: Afro-House's Sacred Warehouse Rituals", "tree_type": "collection", "type": "tree_node"}, "tracks": [null, null, null, null, null, null, null, {"artist": "Mim Suleiman", "bpm": 130, "bpm_level": 130, "has_audio": true, "id": 1495, "key": "4M", "title": "Haki", "year": 2012}, null, null]}, {"id": "slot-1773409842235-o515", "selectedTrackIndex": null, "source": null, "tracks": []}, {"id": "slot-1773409842235-062b", "selectedTrackIndex": null, "source": null, "tracks": []}, {"id": "slot-1773409842235-e6b4", "selectedTrackIndex": null, "source": null, "tracks": []}], "set_id": "fc2478c6", "set_name": "Auto Set \u2014 African Rhythms: Roots to Ritual (1970s-2020s)", "phase_profile_id": "classic_arc"}